slideagent/__init__.py
slideagent/__main__.py
slideagent/cli.py
slideagent/context.py
slideagent/workspace.py
slideagent/mcp/__init__.py
slideagent/mcp/server.py
slideagent/mcp/server_complete.py
slideagent/mcp/server_original.py
slideagent/resources/contexts/.aider
slideagent/resources/contexts/.cursorrules
slideagent/resources/contexts/.goose
slideagent/resources/contexts/.windsurfrules
slideagent/resources/contexts/AGENT.md
slideagent/resources/contexts/CLAUDE.md
slideagent/resources/contexts/GEMINI.md
slideagent/resources/contexts/QWEN.md
slideagent/resources/contexts/__init__.py
slideagent/resources/js/package.json
slideagent/resources/js/pdf_generator.js
slideagent/resources/js/live_viewer/live_viewer_server.js
slideagent/resources/js/live_viewer/viewer_client.js
slideagent/resources/js/live_viewer/viewer_styles.css
slideagent/resources/js/live_viewer/viewer_template.html
slideagent/resources/js/live_viewer/modules/config.js
slideagent/resources/js/live_viewer/modules/file_monitor.js
slideagent/resources/js/live_viewer/modules/logger.js
slideagent/resources/js/live_viewer/modules/outline_parser.js
slideagent/resources/js/live_viewer/modules/routes.js
slideagent/resources/templates/charts/bar_chart.py
slideagent/resources/templates/charts/boilerplate.py
slideagent/resources/templates/charts/line_chart.py
slideagent/resources/templates/charts/pie_chart.py
slideagent/resources/templates/charts/stacked_bar.py
slideagent/resources/templates/outlines/outline_report.md
slideagent/resources/templates/outlines/outline_slides.md
slideagent/resources/templates/reports/01_body_page.html
slideagent/resources/templates/reports/02_cover_page.html
slideagent/resources/templates/reports/03_table_of_contents.html
slideagent/resources/templates/reports/04_section_divider.html
slideagent/resources/templates/reports/05_executive_summary.html
slideagent/resources/templates/reports/06_quote_page.html
slideagent/resources/templates/reports/99_endnotes.html
slideagent-1.0.3.dist-info/METADATA
slideagent-1.0.3.dist-info/WHEEL
slideagent-1.0.3.dist-info/entry_points.txt
slideagent-1.0.3.dist-info/licenses/LICENSE
slideagent-1.0.3.dist-info/RECORD
