Metadata-Version: 2.4
Name: slideagent
Version: 1.0.3
Summary: MCP server for AI-powered presentation generation - create slides, charts, and PDFs with Claude Desktop
Project-URL: Homepage, https://github.com/flong28/slideagent
Project-URL: Repository, https://github.com/flong28/slideagent
Project-URL: Issues, https://github.com/flong28/slideagent/issues
Project-URL: Documentation, https://github.com/flong28/slideagent#readme
Author-email: Frank Long <slideagent.mcp@gmail.com>
License: MIT
License-File: LICENSE
Keywords: ai,automation,charts,claude,mcp,pdf,presentations,slides
Classifier: Development Status :: 4 - Beta
Classifier: Intended Audience :: Developers
Classifier: Intended Audience :: End Users/Desktop
Classifier: License :: OSI Approved :: MIT License
Classifier: Operating System :: OS Independent
Classifier: Programming Language :: Python :: 3
Classifier: Programming Language :: Python :: 3.8
Classifier: Programming Language :: Python :: 3.9
Classifier: Programming Language :: Python :: 3.10
Classifier: Programming Language :: Python :: 3.11
Classifier: Programming Language :: Python :: 3.12
Classifier: Topic :: Multimedia :: Graphics :: Presentation
Classifier: Topic :: Office/Business :: Office Suites
Requires-Python: >=3.8
Requires-Dist: beautifulsoup4>=4.13.4
Requires-Dist: fastmcp>=2.11.3
Requires-Dist: jinja2>=3.1.0
Requires-Dist: matplotlib>=3.7.0
Requires-Dist: mcp>=0.1.0
Requires-Dist: pandas>=2.0.0
Requires-Dist: pyyaml>=6.0
Provides-Extra: dev
Requires-Dist: black>=23.0.0; extra == 'dev'
Requires-Dist: build>=0.10.0; extra == 'dev'
Requires-Dist: pytest>=7.0.0; extra == 'dev'
Requires-Dist: ruff>=0.1.0; extra == 'dev'
Requires-Dist: twine>=4.0.0; extra == 'dev'
